pytas/TA_merge_matrices.py
pytas/TA_plot_matrix.py
pytas/TA_t0_correction_and_background_removal.py
pytas/__init__.py
pytas/_version.py
pytas/shared_functions_classes.py
pytas-1.2.7.dist-info/licenses/LICENSE
pytas-1.2.7.dist-info/METADATA
pytas-1.2.7.dist-info/WHEEL
pytas-1.2.7.dist-info/top_level.txt
pytas-1.2.7.dist-info/RECORD
