Metadata-Version: 2.4
Name: pytas
Version: 1.2.7
Summary: A python, matplotlib, and QT based GUI for transient absorption processing.
Author-email: damonturney <damonturney@gmail.com>
License: MIT
Requires-Python: >=3.8
License-File: LICENSE
Requires-Dist: numpy>=1.21.0
Requires-Dist: h5py>=3.1.0
Requires-Dist: scipy>=1.7.0
Requires-Dist: matplotlib>=3.5.0
Requires-Dist: PyQt5>=5.15.0
Dynamic: license-file
